[{"parameterName": "@version", "type": "string", "cardinality": "[0..1]", "description": "Web Service version"}, {"parameterName": " @Add_Only", "type": "boolean", "cardinality": "[0..1]", "description": "Add Only"}, {"parameterName": "Award_Group_Reference", "type": "Award_GroupObject", "Award_GroupObject": [{"parameterName": " @Descriptor", "type": "string", "cardinality": "[0..1]", "description": "Display information used to describe an instance of an object. This 'optional' information is for outbound descriptive purposes only and is not processed on inbound Workday Web Services requests."}, {"parameterName": "ID", "type": "Award_GroupObjectID", "Award_GroupObjectID": [{"parameterName": "#text", "type": "string", "cardinality": "", "description": ""}, {"parameterName": " @type", "type": "WID,  Award_Group_ID", "cardinality": "[1..1]", "description": "The unique identifier type. Each \"ID\" for an instance of an object contains a type and a value. A single instance of an object can have multiple \"ID\" but only a single \"ID\" per \"type\".  Some \"types\" require a reference to a parent instance."}], "cardinality": "[0..*]", "description": "Contains a unique identifier for an instance of an object."}], "cardinality": "[0..1]", "description": "Reference to Award Group being submitted."}, {"parameterName": "Award_Group_Data", "type": "Award_Group_Data", "Award_Group_Data": [{"parameterName": "Award_Group_Reference_ID", "type": "string", "cardinality": "[0..1]", "description": "Award Group Reference ID. This is the Award Group Unique Identifier."}, {"parameterName": "Name", "type": "string", "cardinality": "[0..1]", "description": "Name of Award Group", "validation": [{"validation": "The Award Group Name must be unique\u00a0", "description": "\u00a0"}]}, {"parameterName": "Description", "type": "RichText", "RichText": [], "cardinality": "[0..1]", "description": "Description of Award Group"}, {"parameterName": "Award_Contracts_Reference", "type": "Award_ContractObject", "Award_ContractObject": [{"parameterName": " @Descriptor", "type": "string", "cardinality": "[0..1]", "description": "Display information used to describe an instance of an object. This 'optional' information is for outbound descriptive purposes only and is not processed on inbound Workday Web Services requests."}, {"parameterName": "ID", "type": "Award_ContractObjectID", "Award_ContractObjectID": [{"parameterName": "#text", "type": "string", "cardinality": "", "description": ""}, {"parameterName": " @type", "type": "WID,  Award_Reference_ID", "cardinality": "[1..1]", "description": "The unique identifier type. Each \"ID\" for an instance of an object contains a type and a value. A single instance of an object can have multiple \"ID\" but only a single \"ID\" per \"type\".  Some \"types\" require a reference to a parent instance."}], "cardinality": "[0..*]", "description": "Contains a unique identifier for an instance of an object."}], "cardinality": "[0..*]", "description": "Award Contracts belonging to this Award Group"}, {"parameterName": "Inactive", "type": "boolean", "cardinality": "[0..1]", "description": "Set to True means this Award Group is no longer active."}], "cardinality": "[1..1]", "description": "This element contains all of the data to describe an Award Group in Workday."}]