[{"parameterName": "@version", "type": "string", "cardinality": "[0..1]", "description": "Web Service version"}, {"parameterName": " @Add_Only", "type": "boolean", "cardinality": "[0..1]", "description": "Prevents updating existing budget check options sets."}, {"parameterName": "Budget_Check_Options_Set_Reference", "type": "Budget_Check_Options_SetObject", "Budget_Check_Options_SetObject": [{"parameterName": " @Descriptor", "type": "string", "cardinality": "[0..1]", "description": "Display information used to describe an instance of an object. This 'optional' information is for outbound descriptive purposes only and is not processed on inbound Workday Web Services requests."}, {"parameterName": "ID", "type": "Budget_Check_Options_SetObjectID", "Budget_Check_Options_SetObjectID": [{"parameterName": "#text", "type": "string", "cardinality": "", "description": ""}, {"parameterName": " @type", "type": "WID,  Budget_Check_Options_Set_ID,  Budgetary_Control_Options_ID", "cardinality": "[1..1]", "description": "The unique identifier type. Each \"ID\" for an instance of an object contains a type and a value. A single instance of an object can have multiple \"ID\" but only a single \"ID\" per \"type\".  Some \"types\" require a reference to a parent instance."}], "cardinality": "[0..*]", "description": "Contains a unique identifier for an instance of an object."}], "cardinality": "[0..1]", "description": "Budget check options set reference to update. Blank if adding a budget check options set."}, {"parameterName": "Budget_Check_Options_Set_Data", "type": "Budget_Check_Options_Set_Data", "Budget_Check_Options_Set_Data": [{"parameterName": "Budget_Check_Options_Set_ID", "type": "string", "cardinality": "[0..1]", "description": "Budget check options set reference ID."}, {"parameterName": "Budget_Check_Options_Set_Name", "type": "string", "cardinality": "[1..1]", "description": "Budget check options set name.", "validation": [{"validation": "Enter a Budget Check Options Set name that isn't already in use.\u00a0", "description": "Enter a Budget Check Options Set name that isn't already in use.\u00a0"}]}, {"parameterName": "Primary", "type": "boolean", "cardinality": "[0..1]", "description": "Budget check options set primary flag.", "validation": [{"validation": "Select only 1 Budget Check Options Set as primary.\u00a0", "description": "Select only 1 Budget Check Options Set as primary.\u00a0"}]}, {"parameterName": "Enable_Budget_Check", "type": "boolean", "cardinality": "[0..1]", "description": "Select to enable budget check for the budget check options set.", "validation": [{"validation": "Set Enable Budget Check to True to select Ledger Types.\u00a0", "description": "Set Enable Budget Check to True to select Ledger Types.\u00a0"}, {"validation": "Set Enable Budget Check to True to select Cumulative Control Periods.\u00a0", "description": "Set Enable Budget Check to True to select Cumulative Control Periods.\u00a0"}, {"validation": "Set Enable Budget Check to True to select an Evaluation Date.\u00a0", "description": "Set Enable Budget Check to True to select an Evaluation Date.\u00a0"}, {"validation": "Set Enable Budget Check to True to select Allow Budget Check Override.\u00a0", "description": "Set Enable Budget Check to True to select Allow Budget Check Override.\u00a0"}, {"validation": "Set Enable Budget Check to True to select Control by Duration.\u00a0", "description": "Set Enable Budget Check to True to select Control by Duration.\u00a0"}, {"validation": "Set Enable Budget Check to True to select Control by Award Entry Period.\u00a0", "description": "Set Enable Budget Check to True to select Control by Award Entry Period.\u00a0"}, {"validation": "Set Enable Budget Check to True to select a Budget Check Option.\u00a0", "description": "Set Enable Budget Check to True to select a Budget Check Option.\u00a0"}]}, {"parameterName": "Include_Reserved_Journal_Lines", "type": "boolean", "cardinality": "[0..1]", "description": "Budget check options set includes reserved journal lines for budget check."}, {"parameterName": "Allow_Credit_Transactions_to_Pass", "type": "boolean", "cardinality": "[0..1]", "description": "Budget check options set allows credit transactions to pass budget check."}, {"parameterName": "Budget_Check_Option_Reference", "type": "Budget_Check_OptionObject", "Budget_Check_OptionObject": [{"parameterName": " @Descriptor", "type": "string", "cardinality": "[0..1]", "description": "Display information used to describe an instance of an object. This 'optional' information is for outbound descriptive purposes only and is not processed on inbound Workday Web Services requests."}, {"parameterName": "ID", "type": "Budget_Check_OptionObjectID", "Budget_Check_OptionObjectID": [{"parameterName": "#text", "type": "string", "cardinality": "", "description": ""}, {"parameterName": " @type", "type": "WID,  Budget_Check_Option_ID", "cardinality": "[1..1]", "description": "The unique identifier type. Each \"ID\" for an instance of an object contains a type and a value. A single instance of an object can have multiple \"ID\" but only a single \"ID\" per \"type\".  Some \"types\" require a reference to a parent instance."}], "cardinality": "[0..*]", "description": "Contains a unique identifier for an instance of an object."}], "cardinality": "[0..1]", "description": "Budget check option for budget check option set.", "validation": [{"validation": "Change Budget Check Option to Control to allow budget check override.\u00a0", "description": "Change Budget Check Option to Control to allow budget check override.\u00a0"}, {"validation": "Select a Budget Check Option to enable budget check.\u00a0", "description": "Select a Budget Check Option to enable budget check.\u00a0"}]}, {"parameterName": "Evaluation_Date_Reference", "type": "Evaluation_DateObject", "Evaluation_DateObject": [{"parameterName": " @Descriptor", "type": "string", "cardinality": "[0..1]", "description": "Display information used to describe an instance of an object. This 'optional' information is for outbound descriptive purposes only and is not processed on inbound Workday Web Services requests."}, {"parameterName": "ID", "type": "Evaluation_DateObjectID", "Evaluation_DateObjectID": [{"parameterName": "#text", "type": "string", "cardinality": "", "description": ""}, {"parameterName": " @type", "type": "WID,  Evaluation_Date_ID", "cardinality": "[1..1]", "description": "The unique identifier type. Each \"ID\" for an instance of an object contains a type and a value. A single instance of an object can have multiple \"ID\" but only a single \"ID\" per \"type\".  Some \"types\" require a reference to a parent instance."}], "cardinality": "[0..*]", "description": "Contains a unique identifier for an instance of an object."}], "cardinality": "[0..1]", "description": "Budget check options set evaluation date.", "validation": [{"validation": "Select an Evaluation Date to enable budget check.\u00a0", "description": "Select an Evaluation Date to enable budget check.\u00a0"}]}, {"parameterName": "Cumulative_Control_Periods", "type": "boolean", "cardinality": "[0..1]", "description": "Budget check options set has cumulative control periods."}, {"parameterName": "Control_by_Award_Entry_Period [Choice] ", "type": "boolean", "cardinality": "[0..1]", "description": "Budget check options set controls by award entry period.", "validation": [{"validation": "Select Control by Award Entry Period or Control by Duration to enable budget check.\u00a0", "description": "Select Control by Award Entry Period or Control by Duration to enable budget check.\u00a0"}]}, {"parameterName": "Control_by_Duration [Choice] ", "type": "boolean", "cardinality": "[0..1]", "description": "Budget check options set controls by duration.", "validation": [{"validation": "Select Control by Award Entry Period or Control by Duration to enable budget check.\u00a0", "description": "Select Control by Award Entry Period or Control by Duration to enable budget check.\u00a0"}]}, {"parameterName": "Ledger_Type_Reference", "type": "Ledger_TypeObject", "Ledger_TypeObject": [{"parameterName": " @Descriptor", "type": "string", "cardinality": "[0..1]", "description": "Display information used to describe an instance of an object. This 'optional' information is for outbound descriptive purposes only and is not processed on inbound Workday Web Services requests."}, {"parameterName": "ID", "type": "Ledger_TypeObjectID", "Ledger_TypeObjectID": [{"parameterName": "#text", "type": "string", "cardinality": "", "description": ""}, {"parameterName": " @type", "type": "WID,  Ledger_Type_ID", "cardinality": "[1..1]", "description": "The unique identifier type. Each \"ID\" for an instance of an object contains a type and a value. A single instance of an object can have multiple \"ID\" but only a single \"ID\" per \"type\".  Some \"types\" require a reference to a parent instance."}], "cardinality": "[0..*]", "description": "Contains a unique identifier for an instance of an object."}], "cardinality": "[0..*]", "description": "Budget check options set ledger types."}, {"parameterName": "Allow_Budget_Check_Override", "type": "boolean", "cardinality": "[0..1]", "description": "Budget check options set allows budget check override."}], "cardinality": "[0..1]", "description": "The budget check options set data."}]