[{"parameterName": "@version", "type": "string", "cardinality": "[0..1]", "description": "Web Service version"}, {"parameterName": " @Add_Only", "type": "boolean", "cardinality": "[0..1]", "description": "Add Only boolean that signifies that the Feedback Badge will be added."}, {"parameterName": "Delete", "type": "boolean", "cardinality": "[0..1]", "description": "Delete boolean that signifies that the Feedback Badge will be deleted."}, {"parameterName": "Feedback__Badge_Reference", "type": "Feedback_BadgeObject", "Feedback_BadgeObject": [{"parameterName": " @Descriptor", "type": "string", "cardinality": "[0..1]", "description": "Display information used to describe an instance of an object. This 'optional' information is for outbound descriptive purposes only and is not processed on inbound Workday Web Services requests."}, {"parameterName": "ID", "type": "Feedback_BadgeObjectID", "Feedback_BadgeObjectID": [{"parameterName": "#text", "type": "string", "cardinality": "", "description": ""}, {"parameterName": " @type", "type": "WID,  Feedback_Badge_ID", "cardinality": "[1..1]", "description": "The unique identifier type. Each \"ID\" for an instance of an object contains a type and a value. A single instance of an object can have multiple \"ID\" but only a single \"ID\" per \"type\".  Some \"types\" require a reference to a parent instance."}], "cardinality": "[0..*]", "description": "Contains a unique identifier for an instance of an object."}], "cardinality": "[0..1]", "description": "Feedback Badge Reference."}, {"parameterName": "Feedback_Badge_Data", "type": "Feedback_Badge_Data", "Feedback_Badge_Data": [{"parameterName": "ID", "type": "string", "cardinality": "[0..1]", "description": "The ID of a Feedback Badge."}, {"parameterName": "Feedback_Badge_Name", "type": "string", "cardinality": "[0..1]", "description": "The Name for a Feedback Badge.", "validation": [{"validation": "You can't change the name of an inactive badge.\u00a0", "description": "\u00a0"}]}, {"parameterName": "Icon_Reference", "type": "IconObject", "IconObject": [{"parameterName": " @Descriptor", "type": "string", "cardinality": "[0..1]", "description": "Display information used to describe an instance of an object. This 'optional' information is for outbound descriptive purposes only and is not processed on inbound Workday Web Services requests."}, {"parameterName": "ID", "type": "IconObjectID", "IconObjectID": [{"parameterName": "#text", "type": "string", "cardinality": "", "description": ""}, {"parameterName": " @type", "type": "WID,  Icon_ID", "cardinality": "[1..1]", "description": "The unique identifier type. Each \"ID\" for an instance of an object contains a type and a value. A single instance of an object can have multiple \"ID\" but only a single \"ID\" per \"type\".  Some \"types\" require a reference to a parent instance."}], "cardinality": "[0..*]", "description": "Contains a unique identifier for an instance of an object."}], "cardinality": "[0..1]", "description": "The Icon for a Feedback Badge."}, {"parameterName": "Inactive", "type": "boolean", "cardinality": "[0..1]", "description": "The Inactive boolean for Feedback badge which determines whether or not a feedback badge is inactive."}], "cardinality": "[1..1]", "description": "Element which contains the ID, Feedback Badge Name, Icon, and Inactive boolean for a Feedback Badge.", "validation": [{"validation": "Select a Workday-delivered icon associated with feedback badges.\u00a0", "description": "\u00a0"}]}]