[{"parameterName": "@version", "type": "string", "cardinality": "[0..1]", "description": "Web Service version"}, {"parameterName": "Campaign_Category_Reference", "type": "Campaign_Category__All_Object", "Campaign_Category__All_Object": [{"parameterName": " @Descriptor", "type": "string", "cardinality": "[0..1]", "description": "Display information used to describe an instance of an object. This 'optional' information is for outbound descriptive purposes only and is not processed on inbound Workday Web Services requests."}, {"parameterName": "ID", "type": "Campaign_Category__All_ObjectID", "Campaign_Category__All_ObjectID": [{"parameterName": "#text", "type": "string", "cardinality": "", "description": ""}, {"parameterName": " @type", "type": "WID,  Campaign_Category_ID", "cardinality": "[1..1]", "description": "The unique identifier type. Each \"ID\" for an instance of an object contains a type and a value. A single instance of an object can have multiple \"ID\" but only a single \"ID\" per \"type\".  Some \"types\" require a reference to a parent instance."}], "cardinality": "[0..*]", "description": "Contains a unique identifier for an instance of an object."}], "cardinality": "[0..1]", "description": "Reference of a Campaign Category for Put Request"}, {"parameterName": "Campaign_Category_Data", "type": "Campaign_Category_Data", "Campaign_Category_Data": [{"parameterName": "Name", "type": "string", "cardinality": "[1..1]", "description": "Name for Campaign Category", "validation": [{"validation": "Select a different Campaign Category Name. [name] is already in use.\u00a0", "description": "\u00a0"}]}, {"parameterName": "Description", "type": "string", "cardinality": "[0..1]", "description": "Description for Campaign Category"}, {"parameterName": "Campaign_Type_Reference", "type": "Connect_Campaign_TypeObject", "Connect_Campaign_TypeObject": [{"parameterName": " @Descriptor", "type": "string", "cardinality": "[0..1]", "description": "Display information used to describe an instance of an object. This 'optional' information is for outbound descriptive purposes only and is not processed on inbound Workday Web Services requests."}, {"parameterName": "ID", "type": "Connect_Campaign_TypeObjectID", "Connect_Campaign_TypeObjectID": [{"parameterName": "#text", "type": "string", "cardinality": "", "description": ""}, {"parameterName": " @type", "type": "WID,  Campaign_Type_ID", "cardinality": "[1..1]", "description": "The unique identifier type. Each \"ID\" for an instance of an object contains a type and a value. A single instance of an object can have multiple \"ID\" but only a single \"ID\" per \"type\".  Some \"types\" require a reference to a parent instance."}], "cardinality": "[0..*]", "description": "Contains a unique identifier for an instance of an object."}], "cardinality": "[1..1]", "description": "Campaign Type for Campaign Category", "validation": [{"validation": "The Campaign Type is not Valid. Select a Valid Type.\u00a0", "description": "\u00a0"}]}, {"parameterName": "Inactive", "type": "boolean", "cardinality": "[0..1]", "description": "Inactive Flag for Campaign Category"}], "cardinality": "[0..1]", "description": "Data for Campaign Category Put Request"}]